flake8_mock.py
verve_flake8_mock-0.4.dist-info/LICENSE
verve_flake8_mock-0.4.dist-info/METADATA
verve_flake8_mock-0.4.dist-info/WHEEL
verve_flake8_mock-0.4.dist-info/entry_points.txt
verve_flake8_mock-0.4.dist-info/top_level.txt
verve_flake8_mock-0.4.dist-info/RECORD
